{
  "providers": {
    "awscloudformation": {
      "AuthRoleName": "amplify-mycharts-mybeatsdev-155649-authRole",
      "UnauthRoleArn": "arn:aws:iam::185329004895:role/amplify-mycharts-mybeatsdev-155649-unauthRole",
      "AuthRoleArn": "arn:aws:iam::185329004895:role/amplify-mycharts-mybeatsdev-155649-authRole",
      "Region": "us-east-1",
      "DeploymentBucketName": "amplify-mycharts-mybeatsdev-155649-deployment",
      "UnauthRoleName": "amplify-mycharts-mybeatsdev-155649-unauthRole",
      "StackName": "amplify-mycharts-mybeatsdev-155649",
      "StackId": "arn:aws:cloudformation:us-east-1:185329004895:stack/amplify-mycharts-mybeatsdev-155649/703eb440-0f07-11ef-9634-125646cbad59",
      "AmplifyAppId": "ddm2mcfjjdp49"
    }
  },
  "api": {
    "mycharts": {
      "dependsOn": [],
      "output": {
        "authConfig": {
          "additionalAuthenticationProviders": [
            {
              "authenticationType": "AWS_IAM"
            }
          ],
          "defaultAuthentication": {
            "apiKeyConfig": {
              "apiKeyExpirationDays": 30,
              "description": "api key description"
            },
            "authenticationType": "API_KEY"
          }
        },
        "GraphQLAPIIdOutput": "oarhl4rq6na3hffd5vdcfijjby",
        "GraphQLAPIEndpointOutput": "https://pct7bjkorngxjh53oirmrlvgga.appsync-api.us-east-1.amazonaws.com/graphql",
        "GraphQLAPIKeyOutput": "da2-ozmnzdmgrbbvjiqep3nqihy3li"
      },
      "providerPlugin": "awscloudformation",
      "service": "AppSync",
      "lastPushTimeStamp": "2024-05-10T20:18:40.502Z",
      "providerMetadata": {
        "s3TemplateURL": "https://s3.amazonaws.com/amplify-mycharts-mybeatsdev-155649-deployment/amplify-cfn-templates/api/cloudformation-template.json",
        "logicalId": "apimycharts"
      },
      "lastPushDirHash": "G9FIri4T+efBZ4CSWWS/2KsCnP4="
    }
  },
  "auth": {
    "mycharts1ff09fda": {
      "customAuth": false,
      "dependsOn": [],
      "frontendAuthConfig": {
        "mfaConfiguration": "OFF",
        "mfaTypes": [
          "SMS"
        ],
        "passwordProtectionSettings": {
          "passwordPolicyMinLength": 8,
          "passwordPolicyCharacters": []
        },
        "signupAttributes": [
          "EMAIL"
        ],
        "socialProviders": [],
        "usernameAttributes": [],
        "verificationMechanisms": [
          "EMAIL"
        ]
      },
      "providerPlugin": "awscloudformation",
      "service": "Cognito",
      "providerMetadata": {
        "s3TemplateURL": "https://s3.amazonaws.com/amplify-mycharts-mybeatsdev-155649-deployment/amplify-cfn-templates/auth/mycharts1ff09fda-cloudformation-template.json",
        "logicalId": "authmycharts1ff09fda"
      },
      "lastPushTimeStamp": "2024-05-10T20:18:40.502Z",
      "output": {
        "UserPoolId": "us-east-1_aL8A6SwZz",
        "AppClientIDWeb": "2ptgtn65j2tmq6nmm4fudq0946",
        "AppClientID": "1neup9oe4e73mgq65p3ejbvp2l",
        "IdentityPoolId": "us-east-1:8a25f978-80f4-44e0-a6b1-55550d55fc8a",
        "UserPoolArn": "arn:aws:cognito-idp:us-east-1:185329004895:userpool/us-east-1_aL8A6SwZz",
        "IdentityPoolName": "mycharts1ff09fda_identitypool_1ff09fda__mybeatsdev",
        "UserPoolName": "mycharts1ff09fda_userpool_1ff09fda"
      },
      "lastPushDirHash": "CgvYpcWgEoSgdY2vcDzzFyZHywE="
    }
  },
  "storage": {
    "myCharts": {
      "dependsOn": [],
      "providerPlugin": "awscloudformation",
      "service": "S3",
      "lastPushTimeStamp": "2024-05-10T20:18:40.502Z",
      "providerMetadata": {
        "s3TemplateURL": "https://s3.amazonaws.com/amplify-mycharts-mybeatsdev-155649-deployment/amplify-cfn-templates/storage/cloudformation-template.json",
        "logicalId": "storagemyCharts"
      },
      "output": {
        "BucketName": "firebeats155649-mybeatsdev",
        "Region": "us-east-1"
      },
      "lastPushDirHash": "H7n+qsC8z1AkR7uQVS/YMZs6jOM="
    }
  }
}